ThirdcamelArabicReader/__init__.py
ThirdcamelArabicReader/six.py
ThirdcamelArabicReader/cachetools/__init__.py
ThirdcamelArabicReader/cachetools/func.py
ThirdcamelArabicReader/cachetools/keys.py
ThirdcamelArabicReader/camel_tools/__init__.py
ThirdcamelArabicReader/camel_tools/data/__init__.py
ThirdcamelArabicReader/camel_tools/data/downloader.py
ThirdcamelArabicReader/camel_tools/morphology/__init__.py
ThirdcamelArabicReader/camel_tools/morphology/analyzer.py
ThirdcamelArabicReader/camel_tools/morphology/database.py
ThirdcamelArabicReader/camel_tools/morphology/errors.py
ThirdcamelArabicReader/camel_tools/morphology/generator.py
ThirdcamelArabicReader/camel_tools/morphology/give_read.py
ThirdcamelArabicReader/camel_tools/morphology/reinflector.py
ThirdcamelArabicReader/camel_tools/morphology/utils.py
ThirdcamelArabicReader/camel_tools/morphology/cachetools/__init__.py
ThirdcamelArabicReader/camel_tools/morphology/cachetools/func.py
ThirdcamelArabicReader/camel_tools/morphology/cachetools/keys.py
ThirdcamelArabicReader/camel_tools/utils/__init__.py
ThirdcamelArabicReader/camel_tools/utils/charmap.py
ThirdcamelArabicReader/camel_tools/utils/charsets.py
ThirdcamelArabicReader/camel_tools/utils/dediac.py
ThirdcamelArabicReader/camel_tools/utils/normalize.py
ThirdcamelArabicReader/camel_tools/utils/six.py
ThirdcamelArabicReader/camel_tools/utils/stringutils.py
ThirdcamelArabicReader/camel_tools/utils/transliterate.py
CmlArabicReaderThird-0.1.dist-info/LICENSE.txt
CmlArabicReaderThird-0.1.dist-info/METADATA
CmlArabicReaderThird-0.1.dist-info/WHEEL
CmlArabicReaderThird-0.1.dist-info/top_level.txt
CmlArabicReaderThird-0.1.dist-info/RECORD
