Metadata-Version: 2.1
Name: CmlArabicReaderThird
Version: 0.1
Summary: Sends definition of any arabic word
Home-page: UNKNOWN
Author: Anonymous_Shad0w
Author-email: techcomputersandgames@gmail.com
License: UNKNOWN
Platform: UNKNOWN
Classifier: Programming Language :: Python :: 3
Classifier: License :: OSI Approved :: MIT License
Classifier: Operating System :: OS Independent
